onepasswordconnectsdk/__init__.py
onepasswordconnectsdk/async_client.py
onepasswordconnectsdk/client.py
onepasswordconnectsdk/config.py
onepasswordconnectsdk/connect.py
onepasswordconnectsdk/errors.py
onepasswordconnectsdk/models/__init__.py
onepasswordconnectsdk/models/constants.py
onepasswordconnectsdk/models/error.py
onepasswordconnectsdk/models/field.py
onepasswordconnectsdk/models/field_section.py
onepasswordconnectsdk/models/file.py
onepasswordconnectsdk/models/generator_recipe.py
onepasswordconnectsdk/models/item.py
onepasswordconnectsdk/models/item_details.py
onepasswordconnectsdk/models/item_urls.py
onepasswordconnectsdk/models/item_vault.py
onepasswordconnectsdk/models/parsed_field.py
onepasswordconnectsdk/models/parsed_item.py
onepasswordconnectsdk/models/section.py
onepasswordconnectsdk/models/summary_item.py
onepasswordconnectsdk/models/vault.py
onepasswordconnectsdk/serializer.py
onepasswordconnectsdk/utils.py
onepasswordconnectsdk-2.0.0.dist-info/LICENSE.md
onepasswordconnectsdk-2.0.0.dist-info/METADATA
onepasswordconnectsdk-2.0.0.dist-info/WHEEL
onepasswordconnectsdk-2.0.0.dist-info/RECORD
