Metadata-Version: 2.3
Name: onepasswordconnectsdk
Version: 2.0.0
Summary: Python SDK for 1Password Connect
License: MIT
Author: 1Password
Requires-Python: >=3.10,<4.0
Classifier: License :: OSI Approved :: MIT License
Classifier: Programming Language :: Python :: 3
Classifier: Programming Language :: Python :: 3.10
Classifier: Programming Language :: Python :: 3.11
Classifier: Programming Language :: Python :: 3.12
Classifier: Programming Language :: Python :: 3.13
Requires-Dist: httpx (>=0.28.1,<0.29.0)
Requires-Dist: python-dateutil (>=2.8.1,<3.0.0)
Project-URL: Bug Tracker, https://github.com/1Password/connect-sdk-python/issues
Project-URL: Repository, https://github.com/1Password/connect-sdk-python
Project-URL: Report Security Issue, https://bugcrowd.com/agilebits
